venvx/__init__.py
venvx/__main__.py
venvx/console.py
venvx/pstream.py
venvx/shellext.py
venvx/tools.py
venvx/virtualenv.py
venvx/config/__init__.py
venvx/config/defaults.toml
venvx/config/toml.py
venvx-0.4.0.dist-info/entry_points.txt
venvx-0.4.0.dist-info/LICENSE
venvx-0.4.0.dist-info/WHEEL
venvx-0.4.0.dist-info/METADATA
venvx-0.4.0.dist-info/RECORD
