Metadata-Version: 2.1
Name: venvx
Version: 0.4.0
Summary: Easy-to-use virtual environment manager for bash and zsh
Keywords: venv,virtual environments
Author-email: Ralf Luetkemeier <foss@rlue.de>
Requires-Python: >=3.10,<4
Classifier: Development Status :: 3 - Alpha
Classifier: Environment :: Console
Classifier: Intended Audience :: Developers
Classifier: License :: OSI Approved :: MIT License
Classifier: Operating System :: MacOS
Classifier: Operating System :: Microsoft :: Windows
Classifier: Operating System :: POSIX :: Linux
Classifier: Programming Language :: Python :: 3
Classifier: Programming Language :: Python :: 3.10
Classifier: Programming Language :: Python :: 3.11
Classifier: Programming Language :: Python :: 3.12
Classifier: Programming Language :: Python :: 3 :: Only
Classifier: Topic :: Software Development
Classifier: Topic :: Utilities
Requires-Dist: cozyconsole >= 0.4.1
Requires-Dist: rich >=12.0.0, <14.0.0
Requires-Dist: rich_argparse_plus >= 0.3.0
Requires-Dist: tomli >= 2.0.0; python_version < '3.11'
Requires-Dist: pybrownies >= 0.6.0 ; extra == "test"
Requires-Dist: pytest >= 7.2.0 ; extra == "test"
Provides-Extra: test
